{
	"name": "salida_peliculas_2",
	"properties": {
		"linkedServiceName": {
			"referenceName": "storageclaseDF2",
			"type": "LinkedServiceReference"
		},
		"folder": {
			"name": "ClaseDF2/datasets_peliculas"
		},
		"annotations": [],
		"type": "Parquet",
		"typeProperties": {
			"location": {
				"type": "AzureBlobFSLocation",
				"fileName": "movies.parquet",
				"folderPath": "peliculas",
				"fileSystem": "clasedf"
			},
			"compressionCodec": "snappy"
		},
		"schema": []
	},
	"type": "Microsoft.DataFactory/factories/datasets"
}